{
  "schemaVersion": 2,
  "projectPhase": "7b-review-ship",
  "currentFeatureId": "001-health-remediation-wsl-permissions-and-lint",
  "currentTaskFile": "tasks/001-health-remediation-wsl-permissions-and-lint.md",
  "testMode": "post",
  "maintenanceLevel": "standard",
  "automationLevel": "light",
  "advisoryProfile": "standard",
  "forkActivationLevel": "standard",
  "features": {
    "1-authoring-sync-baseline": {
      "spec": "specs/1-authoring-sync-baseline.md",
      "task": "tasks/1-authoring-sync-baseline.md",
      "status": "tested"
    },
    "001-health-remediation-wsl-permissions-and-lint": {
      "spec": "specs/001-health-remediation-wsl-permissions-and-lint.md",
      "task": "tasks/001-health-remediation-wsl-permissions-and-lint.md",
      "status": "tested"
    }
  },
  "activeClaims": [],
  "updatedAt": "2026-03-22T06:37:00-05:00"
}
